sales_reporter/__init__.py
sales_reporter/__main__.py
sales_reporter/data_in_out.py
sales_reporter/data_processing.py
sales_reporter_scochilloff-0.1.1.dist-info/METADATA
sales_reporter_scochilloff-0.1.1.dist-info/WHEEL
sales_reporter_scochilloff-0.1.1.dist-info/top_level.txt
sales_reporter_scochilloff-0.1.1.dist-info/RECORD
