Metadata-Version: 2.1
Name: sales_reporter_scochilloff
Version: 0.1.1
Summary: Пакет, загружающий данные о заказах, группирующий их и выдающий отчет
Author-email: ScoChillOFF <cheatkiller12@gmail.com>
License: MIT
Requires-Python: >=3.12
Requires-Dist: pandas==2.2.3
